{"images":[{"startdate":"20251126","fullstartdate":"202511262300","enddate":"20251127","url":"/th?id=OHR.PierOfEastbourne2025_ES-ES1099940063_1920x1080.jpg&rf=LaDigue_1920x1080.jpg&pid=hp","urlbase":"/th?id=OHR.PierOfEastbourne2025_ES-ES1099940063","copyright":"Muelle de Eastbourne, Sussex Oriental, Inglaterra (© Tolga_TEZCAN/Getty Images)","copyrightlink":"https://www.bing.com/search?q=Sussex+Oriental&form=hpcapt&filters=HpDate%3a%2220251126_2300%22","title":"Cielo, mar y aire","quiz":"/search?q=Bing+homepage+quiz&filters=WQOskey:%22HPQuiz_20251126_PierOfEastbourne2025%22&FORM=HPQUIZ","wp":true,"hsh":"af5e98e77a75576a77699dcf429b5e99","drk":1,"top":1,"bot":1,"hs":[]},{"startdate":"20251125","fullstartdate":"202511252300","enddate":"20251126","url":"/th?id=OHR.OliveGrove_ES-ES8682630168_1920x1080.jpg&rf=LaDigue_1920x1080.jpg&pid=hp","urlbase":"/th?id=OHR.OliveGrove_ES-ES8682630168","copyright":"Olivos en la Sierra de Tramontana, Mallorca, Islas Baleares, España (© cinoby/Getty Images)","copyrightlink":"https://www.bing.com/search?q=D%C3%ADa+mundial+del+Olivo&form=hpcapt&filters=HpDate%3a%2220251125_2300%22","title":"La cuna del oro líquido","quiz":"/search?q=Bing+homepage+quiz&filters=WQOskey:%22HPQuiz_20251125_OliveGrove%22&FORM=HPQUIZ","wp":true,"hsh":"e1ac83ca5bf62b70905a8e3e3f54607f","drk":1,"top":1,"bot":1,"hs":[]},{"startdate":"20251124","fullstartdate":"202511242300","enddate":"20251125","url":"/th?id=OHR.TreviFountain_ES-ES1601085402_1920x1080.jpg&rf=LaDigue_1920x1080.jpg&pid=hp","urlbase":"/th?id=OHR.TreviFountain_ES-ES1601085402","copyright":"Fontana di Trevi en Roma, Italia (© Nico De Pasquale Photography/Getty Images)","copyrightlink":"https://www.bing.com/search?q=Roma&form=hpcapt&filters=HpDate%3a%2220251124_2300%22","title":"Salud, monedas sueltas y amor","quiz":"/search?q=Bing+homepage+quiz&filters=WQOskey:%22HPQuiz_20251124_TreviFountain%22&FORM=HPQUIZ","wp":true,"hsh":"506cfa7f381eb5a1dc64bd76495add31","drk":1,"top":1,"bot":1,"hs":[]},{"startdate":"20251123","fullstartdate":"202511232300","enddate":"20251124","url":"/th?id=OHR.GwailorFort_ES-ES8433830967_1920x1080.jpg&rf=LaDigue_1920x1080.jpg&pid=hp","urlbase":"/th?id=OHR.GwailorFort_ES-ES8433830967","copyright":"Fortaleza de Gwalior, Madhya Pradesh, India (© ImagesofIndia/Shutterstock)","copyrightlink":"https://www.bing.com/search?q=India&form=hpcapt&filters=HpDate%3a%2220251123_2300%22","title":"Secretos tallados en piedra","quiz":"/search?q=Bing+homepage+quiz&filters=WQOskey:%22HPQuiz_20251123_GwailorFort%22&FORM=HPQUIZ","wp":true,"hsh":"0fb62382a525c68c348c40853a0ee7ff","drk":1,"top":1,"bot":1,"hs":[]},{"startdate":"20251122","fullstartdate":"202511222300","enddate":"20251123","url":"/th?id=OHR.MadgascarAmmonite_ES-ES6952842200_1920x1080.jpg&rf=LaDigue_1920x1080.jpg&pid=hp","urlbase":"/th?id=OHR.MadgascarAmmonite_ES-ES6952842200","copyright":"Fósil de amonita de Madagascar (© ThomasLENNE/Shutterstock)","copyrightlink":"https://www.bing.com/search?q=La+Secuencia+de+Fibonacci&form=hpcapt&filters=HpDate%3a%2220251122_2300%22","title":"El código secreto de la naturaleza","quiz":"/search?q=Bing+homepage+quiz&filters=WQOskey:%22HPQuiz_20251122_MadgascarAmmonite%22&FORM=HPQUIZ","wp":true,"hsh":"8f06b73ad9920b09515239232ae40431","drk":1,"top":1,"bot":1,"hs":[]},{"startdate":"20251121","fullstartdate":"202511212300","enddate":"20251122","url":"/th?id=OHR.LeshanBuddha_ES-ES8164485271_1920x1080.jpg&rf=LaDigue_1920x1080.jpg&pid=hp","urlbase":"/th?id=OHR.LeshanBuddha_ES-ES8164485271","copyright":"Gran Buda de Leshan, Sichuan, China (© www.anotherdayattheoffice.org/Getty Images)","copyrightlink":"https://www.bing.com/search?q=Gran+Buda+de+Leshan+China&form=hpcapt&filters=HpDate%3a%2220251121_2300%22","title":"El guardián de las aguas","quiz":"/search?q=Bing+homepage+quiz&filters=WQOskey:%22HPQuiz_20251121_LeshanBuddha%22&FORM=HPQUIZ","wp":true,"hsh":"ba0513d9bd12836a3c1d37f364431e2e","drk":1,"top":1,"bot":1,"hs":[]},{"startdate":"20251120","fullstartdate":"202511202300","enddate":"20251121","url":"/th?id=OHR.SealWaving_ES-ES5901823197_1920x1080.jpg&rf=LaDigue_1920x1080.jpg&pid=hp","urlbase":"/th?id=OHR.SealWaving_ES-ES5901823197","copyright":"Focas comunes en el Parque Estatal Robert Moses, Long Island, Nueva York, EE. UU. (© Vicki Jauron, Babylon and Beyond Photography/Getty Images)","copyrightlink":"https://www.bing.com/search?q=Long+Island&form=hpcapt&filters=HpDate%3a%2220251120_2300%22","title":"El día de la cortesía","quiz":"/search?q=Bing+homepage+quiz&filters=WQOskey:%22HPQuiz_20251120_SealWaving%22&FORM=HPQUIZ","wp":true,"hsh":"028e42a09d8229bb6fb5a1a0e73baab9","drk":1,"top":1,"bot":1,"hs":[]},{"startdate":"20251119","fullstartdate":"202511192300","enddate":"20251120","url":"/th?id=OHR.SaypeGeneva_ES-ES5813016129_1920x1080.jpg&rf=LaDigue_1920x1080.jpg&pid=hp","urlbase":"/th?id=OHR.SaypeGeneva_ES-ES5813016129","copyright":"El artista Saype posa con su obra \"World in Progress\" en la sede de la ONU, Ginebra, Suiza (© Valentin Flauraud/EPA-EFE/Shutterstock)","copyrightlink":"https://www.bing.com/search?q=D%C3%ADa+Mundial+del+Ni%C3%B1o&form=hpcapt&filters=HpDate%3a%2220251119_2300%22","title":"Esbozado en la historia","quiz":"/search?q=Bing+homepage+quiz&filters=WQOskey:%22HPQuiz_20251119_SaypeGeneva%22&FORM=HPQUIZ","wp":false,"hsh":"af947a7ac06e167689a2d93194c3be9b","drk":1,"top":1,"bot":1,"hs":[]}],"tooltips":{"loading":"Cargando...","previous":"Imagen anterior","next":"Siguiente imagen","walle":"Esta imagen no está disponible para su descarga como fondo de pantalla.","walls":"Descarga la imagen. Solo se puede usar como papel tapiz."}}